LICENSE
jazzy_timer/__init__.py
jazzy_timer-0.2.0.dist-info/LICENSE
jazzy_timer-0.2.0.dist-info/METADATA
jazzy_timer-0.2.0.dist-info/WHEEL
jazzy_timer-0.2.0.dist-info/RECORD
