Metadata-Version: 2.1
Name: jazzy-timer
Version: 0.2.0
Summary: An ultra-simple timer decorator, part of the jazzy utilities series.
Home-page: https://github.com/edward-jazzhands/jazzy_timer
License: MIT
Keywords: timer,timing,decorator,profiling,profiler,benchmark,jazzy
Author: Edward Jazzhands
Author-email: ed.jazzhands@gmail.com
Requires-Python: >=3.10,<4.0
Classifier: Development Status :: 3 - Alpha
Classifier: Intended Audience :: Developers
Classifier: License :: OSI Approved :: MIT License
Classifier: Operating System :: OS Independent
Classifier: Programming Language :: Python :: 3
Classifier: Programming Language :: Python :: 3.10
Classifier: Programming Language :: Python :: 3.11
Classifier: Programming Language :: Python :: 3.12
Classifier: Topic :: Software Development :: Libraries :: Python Modules
Classifier: Topic :: Software Development :: Testing
Classifier: Topic :: Utilities
Project-URL: Repository, https://github.com/edward-jazzhands/jazzy_timer
